scraper_helper/__init__.py
scraper_helper/address.py
scraper_helper/html.py
scraper_helper/scrapy.py
scraper_helper/text.py
scraper_helper/url.py
scraper_helper-0.0.8.dist-info/AUTHORS.rst
scraper_helper-0.0.8.dist-info/LICENSE
scraper_helper-0.0.8.dist-info/METADATA
scraper_helper-0.0.8.dist-info/WHEEL
scraper_helper-0.0.8.dist-info/top_level.txt
scraper_helper-0.0.8.dist-info/RECORD
