Metadata-Version: 1.2
Name: scraper-helper
Version: 0.0.8
Summary: Helper functions for web scraping
Home-page: https://github.com/eupendra/scraper-helper
Author: Upendra Singhai
Author-email: upendra@coderecode.com
License: GNU GENERAL PUBLIC LICENSE
Project-URL: Documentation, https://scraper-helper.readthedocs.io/
Project-URL: Changelog, https://scraper-helper.readthedocs.io/en/latest/changelog.html
Project-URL: Issue Tracker, https://github.com/eupendra/scraper-helper/issues
Platform: UNKNOWN
Classifier: Development Status :: 5 - Production/Stable
Classifier: Intended Audience :: Developers
Classifier: License :: OSI Approved :: GNU General Public License v3 (GPLv3)
Classifier: Operating System :: Unix
Classifier: Operating System :: POSIX
Classifier: Operating System :: Microsoft :: Windows
Classifier: Programming Language :: Python
Classifier: Programming Language :: Python :: 3
Classifier: Programming Language :: Python :: 3.7
Classifier: Programming Language :: Python :: 3.8
Classifier: Programming Language :: Python :: 3.9
Classifier: Programming Language :: Python :: Implementation :: CPython
Classifier: Programming Language :: Python :: Implementation :: PyPy
Classifier: Topic :: Utilities
Requires-Python: >=3.6
